pixelripper/__init__.py
pixelripper/audio_extensions.txt
pixelripper/pixelripper.py
pixelripper/video_extensions.txt
pixelripper-0.0.1.dist-info/METADATA
pixelripper-0.0.1.dist-info/WHEEL
pixelripper-0.0.1.dist-info/entry_points.txt
pixelripper-0.0.1.dist-info/licenses/LICENSE.txt
pixelripper-0.0.1.dist-info/RECORD
