Metadata-Version: 2.1
Name: pixelripper
Version: 0.0.1
Summary: Package and CLI for downloading media from a webpage.
Project-URL: Homepage, https://github.com/matt-manes/pixelripper
Project-URL: Documentation, https://github.com/matt-manes/pixelripper/tree/main/docs
Project-URL: Source code, https://github.com/matt-manes/pixelripper/tree/main/src/pixelripper
Author-email: Matt Manes <mattmanes@pm.me>
License-File: LICENSE.txt
Keywords: webscraping
Classifier: License :: OSI Approved :: MIT License
Classifier: Operating System :: OS Independent
Classifier: Programming Language :: Python :: 3
Requires-Python: >=3.10
Requires-Dist: bs4
Requires-Dist: printbuddies
Requires-Dist: pytest
Requires-Dist: requests
Requires-Dist: scrapetools
Requires-Dist: seleniumuser
Requires-Dist: whosyouragent
